pygmentation/__init__.py
pygmentation/__main__.py
pygmentation/color_scheme.py
pygmentation/color_schemes.json
pygmentation/pygmentation.py
pygmentation/scheme.py
pygmentation/show.py
pygmentation-0.1.4.dist-info/LICENSE
pygmentation-0.1.4.dist-info/METADATA
pygmentation-0.1.4.dist-info/WHEEL
pygmentation-0.1.4.dist-info/entry_points.txt
pygmentation-0.1.4.dist-info/top_level.txt
pygmentation-0.1.4.dist-info/RECORD
