Metadata-Version: 2.1
Name: pygmentation
Version: 0.1.4
Summary: A quality-of-life package for colour schemes/palettes and matplotlib plots.
Author: Peter Brookes Chambers
Project-URL: Homepage, https://github.com/ech0-chambers/pygmentation
Classifier: Programming Language :: Python :: 3
Classifier: License :: OSI Approved :: GNU Affero General Public License v3
Classifier: Operating System :: OS Independent
Requires-Python: >=3.8
License-File: LICENSE
Requires-Dist: numpy
Requires-Dist: rich
